slack_logger/__init__.py
slack_logger/py.typed
slack_logger_python-0.7.2.dist-info/LICENSE
slack_logger_python-0.7.2.dist-info/METADATA
slack_logger_python-0.7.2.dist-info/WHEEL
slack_logger_python-0.7.2.dist-info/top_level.txt
slack_logger_python-0.7.2.dist-info/RECORD
