Metadata-Version: 2.1
Name: slack-logger-python
Version: 0.7.2
Summary: Slack logger utilizing python logging interface.
Author-email: GRBurst <GRBurst@protonmail.com>
Project-URL: Homepage, https://github.com/GRBurst/slack-python-logging
Project-URL: Bug Tracker, https://github.com/GRBurst/slack-python-logging/issues
Keywords: slack,python,logging,logger,log,python-logging,Handler,Formatter,logging.Handler,logging.Formatter,monitoring,alerting,slack-api,webhook,slack-logger,messaging,health-check,notification-service,notification
Classifier: Development Status :: 4 - Beta
Classifier: Intended Audience :: Developers
Classifier: License :: OSI Approved :: MIT License
Classifier: Operating System :: OS Independent
Classifier: Programming Language :: Python :: 3
Classifier: Programming Language :: Python :: 3.10
Classifier: Topic :: Communications :: Chat
Classifier: Topic :: Internet :: WWW/HTTP
Classifier: Topic :: Internet :: WWW/HTTP :: Dynamic Content
Classifier: Topic :: System :: Logging
Requires-Python: >=3.10
License-File: LICENSE
Requires-Dist: attrs ~=23.1
Requires-Dist: cattrs ~=23.1
Requires-Dist: slack-sdk ~=3.22
